autopytic/__init__.py
autopytic/__main__.py
autopytic/main.py
autopytic/tools/__init__.py
autopytic/tools/wrapper.py
autopytic/wrapper/__init__.py
autopytic/wrapper/wrapper.py
src/__init__.py
src/main.py
src/wrapper/__init__.py
src/wrapper/wrapper.py
autopytic-1.4.3.dist-info/LICENSE
autopytic-1.4.3.dist-info/METADATA
autopytic-1.4.3.dist-info/WHEEL
autopytic-1.4.3.dist-info/top_level.txt
autopytic-1.4.3.dist-info/RECORD
