Metadata-Version: 2.1
Name: autopytic
Version: 1.4.3
Summary: A autopytic package
Home-page: https://github.com/kruczekrobert/autopytic
Author: Robert Kruczek
Author-email: kruczeknb1@gmail.com
License: UNKNOWN
Platform: UNKNOWN
Classifier: Programming Language :: Python :: 3
Classifier: License :: OSI Approved :: MIT License
Classifier: Operating System :: OS Independent
